{"name": "RandomForestClassifier-dot_1.1.1.1-iat_only-8", "balanced_accuracy": 0.7009518259518259, "classification_report": {"alexa_swan_kettle": {"precision": 1.0, "recall": 0.8888888888888888, "f1-score": 0.9411764705882353, "support": 9}, "aqara_hubM2": {"precision": 0.0, "recall": 0.0, "f1-score": 0.0, "support": 8}, "arlo_camera_pro4": {"precision": 0.9166666666666666, "recall": 1.0, "f1-score": 0.9565217391304348, "support": 11}, "boifun_baby": {"precision": 0.4, "recall": 0.6666666666666666, "f1-score": 0.5, "support": 6}, "bose_speaker": {"precision": 0.8333333333333334, "recall": 0.5555555555555556, "f1-score": 0.6666666666666667, "support": 9}, "cosori_air_fryer": {"precision": 0.5833333333333334, "recall": 0.7777777777777778, "f1-score": 0.6666666666666666, "support": 9}, "echodot5": {"precision": 0.11764705882352941, "recall": 0.6666666666666666, "f1-score": 0.2, "support": 3}, "google_nest_doorbell": {"precision": 0.8, "recall": 0.6153846153846154, "f1-score": 0.6956521739130435, "support": 13}, "google_nest_hub": {"precision": 0.7142857142857143, "recall": 0.625, "f1-score": 0.6666666666666666, "support": 8}, "govee_strip_light": {"precision": 1.0, "recall": 1.0, "f1-score": 1.0, "support": 14}, "iROBOT_roomba": {"precision": 0.29411764705882354, "recall": 1.0, "f1-score": 0.45454545454545453, "support": 5}, "nest_cam": {"precision": 0.8, "recall": 0.2857142857142857, "f1-score": 0.4210526315789473, "support": 14}, "netatmo_weather_station": {"precision": 1.0, "recall": 0.16666666666666666, "f1-score": 0.2857142857142857, "support": 6}, "petsafe_feeder": {"precision": 1.0, "recall": 0.4, "f1-score": 0.5714285714285715, "support": 10}, "ring_chime_pro": {"precision": 0.6666666666666666, "recall": 0.6, "f1-score": 0.631578947368421, "support": 10}, "simplicam": {"precision": 1.0, "recall": 1.0, "f1-score": 1.0, "support": 8}, "sonos_speaker": {"precision": 1.0, "recall": 0.8333333333333334, "f1-score": 0.9090909090909091, "support": 12}, "switchbot_hub_mini_1": {"precision": 0.75, "recall": 1.0, "f1-score": 0.8571428571428571, "support": 9}, "vtech_baby_monitor": {"precision": 0.9090909090909091, "recall": 1.0, "f1-score": 0.9523809523809523, "support": 10}, "withings_sleep_analyser": {"precision": 0.75, "recall": 1.0, "f1-score": 0.8571428571428571, "support": 3}, "wiz_smart_bulb": {"precision": 0.625, "recall": 0.625, "f1-score": 0.625, "support": 8}, "wyze_cam_pan_v2": {"precision": 0.7142857142857143, "recall": 0.7142857142857143, "f1-score": 0.7142857142857143, "support": 7}, "accuracy": 0.6979166666666666, "macro avg": {"precision": 0.7215648656156678, "recall": 0.7009518259518259, "f1-score": 0.6623960711050311, "support": 192}, "weighted avg": {"precision": 0.7715037719633308, "recall": 0.6979166666666666, "f1-score": 0.6958311390397639, "support": 192}}}
