{"name": "RandomForestClassifier-doh_8.8.4.4-iat_only-5", "balanced_accuracy": 0.6454628704628704, "classification_report": {"alexa_swan_kettle": {"precision": 0.8571428571428571, "recall": 0.8571428571428571, "f1-score": 0.8571428571428571, "support": 7}, "aqara_hubM2": {"precision": 0.0, "recall": 0.0, "f1-score": 0.0, "support": 4}, "arlo_camera_pro4": {"precision": 0.8333333333333334, "recall": 1.0, "f1-score": 0.9090909090909091, "support": 5}, "boifun_baby": {"precision": 0.42857142857142855, "recall": 0.6666666666666666, "f1-score": 0.5217391304347826, "support": 9}, "bose_speaker": {"precision": 0.5, "recall": 0.4, "f1-score": 0.4444444444444445, "support": 10}, "cosori_air_fryer": {"precision": 0.125, "recall": 0.14285714285714285, "f1-score": 0.13333333333333333, "support": 7}, "echodot5": {"precision": 0.2857142857142857, "recall": 0.8, "f1-score": 0.4210526315789473, "support": 5}, "google_nest_doorbell": {"precision": 0.75, "recall": 0.5, "f1-score": 0.6, "support": 12}, "google_nest_hub": {"precision": 0.9090909090909091, "recall": 0.7692307692307693, "f1-score": 0.8333333333333333, "support": 13}, "govee_strip_light": {"precision": 1.0, "recall": 0.9333333333333333, "f1-score": 0.9655172413793104, "support": 15}, "iROBOT_roomba": {"precision": 0.0, "recall": 0.0, "f1-score": 0.0, "support": 10}, "nest_cam": {"precision": 0.8, "recall": 0.3333333333333333, "f1-score": 0.47058823529411764, "support": 12}, "netatmo_weather_station": {"precision": 0.23529411764705882, "recall": 1.0, "f1-score": 0.38095238095238093, "support": 4}, "petsafe_feeder": {"precision": 1.0, "recall": 0.35714285714285715, "f1-score": 0.5263157894736842, "support": 14}, "ring_chime_pro": {"precision": 0.6, "recall": 0.3333333333333333, "f1-score": 0.42857142857142855, "support": 9}, "simplicam": {"precision": 1.0, "recall": 1.0, "f1-score": 1.0, "support": 3}, "sonos_speaker": {"precision": 1.0, "recall": 0.8571428571428571, "f1-score": 0.923076923076923, "support": 7}, "switchbot_hub_mini_1": {"precision": 0.6875, "recall": 1.0, "f1-score": 0.8148148148148148, "support": 11}, "vtech_baby_monitor": {"precision": 0.9285714285714286, "recall": 1.0, "f1-score": 0.962962962962963, "support": 13}, "withings_sleep_analyser": {"precision": 0.8888888888888888, "recall": 1.0, "f1-score": 0.9411764705882353, "support": 8}, "wiz_smart_bulb": {"precision": 0.14285714285714285, "recall": 0.25, "f1-score": 0.18181818181818182, "support": 4}, "wyze_cam_pan_v2": {"precision": 0.6666666666666666, "recall": 1.0, "f1-score": 0.8, "support": 10}, "accuracy": 0.6458333333333334, "macro avg": {"precision": 0.6199377753856363, "recall": 0.6454628704628704, "f1-score": 0.5961786849223022, "support": 192}, "weighted avg": {"precision": 0.682655594592635, "recall": 0.6458333333333334, "f1-score": 0.62935612656862, "support": 192}}}
