{"name": "RandomForestClassifier-doh_NextDNS-padding_random_block_up-10", "balanced_accuracy": 0.7083333333333334, "classification_report": {"alexa_swan_kettle": {"precision": 0.8333333333333334, "recall": 1.0, "f1-score": 0.9090909090909091, "support": 10}, "aqara_hubM2": {"precision": 0.0, "recall": 0.0, "f1-score": 0.0, "support": 7}, "arlo_camera_pro4": {"precision": 1.0, "recall": 0.875, "f1-score": 0.9333333333333333, "support": 8}, "boifun_baby": {"precision": 0.6153846153846154, "recall": 0.8888888888888888, "f1-score": 0.7272727272727274, "support": 9}, "bose_speaker": {"precision": 0.8181818181818182, "recall": 1.0, "f1-score": 0.9, "support": 9}, "cosori_air_fryer": {"precision": 0.5384615384615384, "recall": 0.7, "f1-score": 0.608695652173913, "support": 10}, "echodot5": {"precision": 0.7, "recall": 0.875, "f1-score": 0.7777777777777777, "support": 8}, "google_nest_doorbell": {"precision": 1.0, "recall": 0.2, "f1-score": 0.33333333333333337, "support": 10}, "google_nest_hub": {"precision": 0.8571428571428571, "recall": 0.6, "f1-score": 0.7058823529411764, "support": 10}, "govee_strip_light": {"precision": 0.6666666666666666, "recall": 1.0, "f1-score": 0.8, "support": 10}, "iROBOT_roomba": {"precision": 0.45454545454545453, "recall": 1.0, "f1-score": 0.625, "support": 10}, "nest_cam": {"precision": 1.0, "recall": 0.3, "f1-score": 0.4615384615384615, "support": 10}, "netatmo_weather_station": {"precision": 0.0, "recall": 0.0, "f1-score": 0.0, "support": 5}, "petsafe_feeder": {"precision": 1.0, "recall": 0.2, "f1-score": 0.33333333333333337, "support": 10}, "ring_chime_pro": {"precision": 0.5625, "recall": 1.0, "f1-score": 0.72, "support": 9}, "simplicam": {"precision": 1.0, "recall": 1.0, "f1-score": 1.0, "support": 9}, "sonos_speaker": {"precision": 0.8333333333333334, "recall": 0.5555555555555556, "f1-score": 0.6666666666666667, "support": 9}, "switchbot_hub_mini_1": {"precision": 0.7142857142857143, "recall": 1.0, "f1-score": 0.8333333333333333, "support": 10}, "vtech_baby_monitor": {"precision": 1.0, "recall": 1.0, "f1-score": 1.0, "support": 10}, "withings_sleep_analyser": {"precision": 0.8888888888888888, "recall": 1.0, "f1-score": 0.9411764705882353, "support": 8}, "wiz_smart_bulb": {"precision": 0.5714285714285714, "recall": 0.5, "f1-score": 0.5333333333333333, "support": 8}, "wyze_cam_pan_v2": {"precision": 0.8, "recall": 0.8888888888888888, "f1-score": 0.8421052631578948, "support": 9}, "accuracy": 0.7272727272727273, "macro avg": {"precision": 0.7206433087114905, "recall": 0.7083333333333334, "f1-score": 0.6659942249033832, "support": 198}, "weighted avg": {"precision": 0.7454115819646122, "recall": 0.7272727272727273, "f1-score": 0.6832901161190991, "support": 198}}, "confusion_matrix": [[10, 0, 0, 0, 0, 0, 0, 0, 0, 0, 0, 0, 0, 0, 0, 0, 0, 0, 0, 0, 0, 0], [0, 0, 0, 0, 0, 0, 0, 0, 0, 0, 6, 0, 0, 0, 0, 0, 0, 0, 0, 1, 0, 0], [0, 0, 7, 0, 0, 0, 0, 0, 0, 0, 1, 0, 0, 0, 0, 0, 0, 0, 0, 0, 0, 0], [0, 0, 0, 8, 0, 0, 0, 0, 0, 0, 0, 0, 0, 0, 0, 0, 1, 0, 0, 0, 0, 0], [0, 0, 0, 0, 9, 0, 0, 0, 0, 0, 0, 0, 0, 0, 0, 0, 0, 0, 0, 0, 0, 0], [0, 0, 0, 0, 0, 7, 0, 0, 0, 1, 0, 0, 0, 0, 0, 0, 0, 1, 0, 0, 1, 0], [0, 0, 0, 1, 0, 0, 7, 0, 0, 0, 0, 0, 0, 0, 0, 0, 0, 0, 0, 0, 0, 0], [0, 0, 0, 0, 0, 0, 0, 2, 1, 0, 0, 0, 0, 0, 7, 0, 0, 0, 0, 0, 0, 0], [0, 0, 0, 0, 2, 0, 0, 0, 6, 0, 0, 0, 0, 0, 0, 0, 0, 0, 0, 0, 0, 2], [0, 0, 0, 0, 0, 0, 0, 0, 0, 10, 0, 0, 0, 0, 0, 0, 0, 0, 0, 0, 0, 0], [0, 0, 0, 0, 0, 0, 0, 0, 0, 0, 10, 0, 0, 0, 0, 0, 0, 0, 0, 0, 0, 0], [0, 0, 0, 1, 0, 0, 2, 0, 0, 2, 0, 3, 0, 0, 0, 0, 0, 0, 0, 0, 2, 0], [0, 0, 0, 0, 0, 0, 0, 0, 0, 0, 5, 0, 0, 0, 0, 0, 0, 0, 0, 0, 0, 0], [1, 0, 0, 0, 0, 4, 0, 0, 0, 1, 0, 0, 0, 2, 0, 0, 0, 2, 0, 0, 0, 0], [0, 0, 0, 0, 0, 0, 0, 0, 0, 0, 0, 0, 0, 0, 9, 0, 0, 0, 0, 0, 0, 0], [0, 0, 0, 0, 0, 0, 0, 0, 0, 0, 0, 0, 0, 0, 0, 9, 0, 0, 0, 0, 0, 0], [0, 0, 0, 3, 0, 0, 1, 0, 0, 0, 0, 0, 0, 0, 0, 0, 5, 0, 0, 0, 0, 0], [0, 0, 0, 0, 0, 0, 0, 0, 0, 0, 0, 0, 0, 0, 0, 0, 0, 10, 0, 0, 0, 0], [0, 0, 0, 0, 0, 0, 0, 0, 0, 0, 0, 0, 0, 0, 0, 0, 0, 0, 10, 0, 0, 0], [0, 0, 0, 0, 0, 0, 0, 0, 0, 0, 0, 0, 0, 0, 0, 0, 0, 0, 0, 8, 0, 0], [1, 0, 0, 0, 0, 2, 0, 0, 0, 0, 0, 0, 0, 0, 0, 0, 0, 1, 0, 0, 4, 0], [0, 0, 0, 0, 0, 0, 0, 0, 0, 1, 0, 0, 0, 0, 0, 0, 0, 0, 0, 0, 0, 8]]}
