{"name": "RandomForestClassifier-doh_AdGuard-iat_only-12", "balanced_accuracy": 0.8207070707070708, "classification_report": {"alexa_swan_kettle": {"precision": 0.9090909090909091, "recall": 1.0, "f1-score": 0.9523809523809523, "support": 10}, "aqara_hubM2": {"precision": 0.0, "recall": 0.0, "f1-score": 0.0, "support": 7}, "arlo_camera_pro4": {"precision": 1.0, "recall": 0.625, "f1-score": 0.7692307692307693, "support": 8}, "boifun_baby": {"precision": 0.8181818181818182, "recall": 1.0, "f1-score": 0.9, "support": 9}, "bose_speaker": {"precision": 1.0, "recall": 1.0, "f1-score": 1.0, "support": 9}, "cosori_air_fryer": {"precision": 0.875, "recall": 0.7, "f1-score": 0.7777777777777777, "support": 10}, "echodot5": {"precision": 1.0, "recall": 1.0, "f1-score": 1.0, "support": 8}, "google_nest_doorbell": {"precision": 1.0, "recall": 1.0, "f1-score": 1.0, "support": 10}, "google_nest_hub": {"precision": 1.0, "recall": 0.9, "f1-score": 0.9473684210526316, "support": 10}, "govee_strip_light": {"precision": 0.8333333333333334, "recall": 1.0, "f1-score": 0.9090909090909091, "support": 10}, "iROBOT_roomba": {"precision": 0.42857142857142855, "recall": 0.9, "f1-score": 0.5806451612903225, "support": 10}, "nest_cam": {"precision": 1.0, "recall": 0.6, "f1-score": 0.7499999999999999, "support": 10}, "netatmo_weather_station": {"precision": 0.0, "recall": 0.0, "f1-score": 0.0, "support": 5}, "petsafe_feeder": {"precision": 0.6923076923076923, "recall": 0.9, "f1-score": 0.7826086956521738, "support": 10}, "ring_chime_pro": {"precision": 1.0, "recall": 1.0, "f1-score": 1.0, "support": 9}, "simplicam": {"precision": 1.0, "recall": 1.0, "f1-score": 1.0, "support": 9}, "sonos_speaker": {"precision": 1.0, "recall": 0.8888888888888888, "f1-score": 0.9411764705882353, "support": 9}, "switchbot_hub_mini_1": {"precision": 1.0, "recall": 1.0, "f1-score": 1.0, "support": 10}, "vtech_baby_monitor": {"precision": 0.9090909090909091, "recall": 1.0, "f1-score": 0.9523809523809523, "support": 10}, "withings_sleep_analyser": {"precision": 0.7777777777777778, "recall": 0.875, "f1-score": 0.823529411764706, "support": 8}, "wiz_smart_bulb": {"precision": 0.8, "recall": 1.0, "f1-score": 0.888888888888889, "support": 8}, "wyze_cam_pan_v2": {"precision": 0.75, "recall": 0.6666666666666666, "f1-score": 0.7058823529411765, "support": 9}, "accuracy": 0.8484848484848485, "macro avg": {"precision": 0.8087888121979031, "recall": 0.8207070707070708, "f1-score": 0.8036800346836135, "support": 198}, "weighted avg": {"precision": 0.8343929359080875, "recall": 0.8484848484848485, "f1-score": 0.8297941952883677, "support": 198}}, "confusion_matrix": [[10, 0, 0, 0, 0, 0, 0, 0, 0, 0, 0, 0, 0, 0, 0, 0, 0, 0, 0, 0, 0, 0], [0, 0, 0, 0, 0, 0, 0, 0, 0, 0, 6, 0, 0, 0, 0, 0, 0, 0, 0, 0, 0, 1], [0, 0, 5, 0, 0, 0, 0, 0, 0, 0, 1, 0, 0, 0, 0, 0, 0, 0, 0, 2, 0, 0], [0, 0, 0, 9, 0, 0, 0, 0, 0, 0, 0, 0, 0, 0, 0, 0, 0, 0, 0, 0, 0, 0], [0, 0, 0, 0, 9, 0, 0, 0, 0, 0, 0, 0, 0, 0, 0, 0, 0, 0, 0, 0, 0, 0], [0, 0, 0, 0, 0, 7, 0, 0, 0, 0, 0, 0, 0, 3, 0, 0, 0, 0, 0, 0, 0, 0], [0, 0, 0, 0, 0, 0, 8, 0, 0, 0, 0, 0, 0, 0, 0, 0, 0, 0, 0, 0, 0, 0], [0, 0, 0, 0, 0, 0, 0, 10, 0, 0, 0, 0, 0, 0, 0, 0, 0, 0, 0, 0, 0, 0], [0, 0, 0, 0, 0, 0, 0, 0, 9, 0, 0, 0, 0, 0, 0, 0, 0, 0, 0, 0, 0, 1], [0, 0, 0, 0, 0, 0, 0, 0, 0, 10, 0, 0, 0, 0, 0, 0, 0, 0, 0, 0, 0, 0], [0, 0, 0, 0, 0, 0, 0, 0, 0, 0, 9, 0, 0, 1, 0, 0, 0, 0, 0, 0, 0, 0], [0, 0, 0, 1, 0, 0, 0, 0, 0, 1, 0, 6, 0, 0, 0, 0, 0, 0, 0, 0, 2, 0], [0, 0, 0, 0, 0, 0, 0, 0, 0, 0, 5, 0, 0, 0, 0, 0, 0, 0, 0, 0, 0, 0], [0, 0, 0, 0, 0, 1, 0, 0, 0, 0, 0, 0, 0, 9, 0, 0, 0, 0, 0, 0, 0, 0], [0, 0, 0, 0, 0, 0, 0, 0, 0, 0, 0, 0, 0, 0, 9, 0, 0, 0, 0, 0, 0, 0], [0, 0, 0, 0, 0, 0, 0, 0, 0, 0, 0, 0, 0, 0, 0, 9, 0, 0, 0, 0, 0, 0], [0, 0, 0, 1, 0, 0, 0, 0, 0, 0, 0, 0, 0, 0, 0, 0, 8, 0, 0, 0, 0, 0], [0, 0, 0, 0, 0, 0, 0, 0, 0, 0, 0, 0, 0, 0, 0, 0, 0, 10, 0, 0, 0, 0], [0, 0, 0, 0, 0, 0, 0, 0, 0, 0, 0, 0, 0, 0, 0, 0, 0, 0, 10, 0, 0, 0], [0, 1, 0, 0, 0, 0, 0, 0, 0, 0, 0, 0, 0, 0, 0, 0, 0, 0, 0, 7, 0, 0], [0, 0, 0, 0, 0, 0, 0, 0, 0, 0, 0, 0, 0, 0, 0, 0, 0, 0, 0, 0, 8, 0], [1, 0, 0, 0, 0, 0, 0, 0, 0, 1, 0, 0, 0, 0, 0, 0, 0, 0, 1, 0, 0, 6]]}
