{"name": "RandomForestClassifier-doh_1.1.1.1-iat_only-0", "balanced_accuracy": 0.6886086136086136, "classification_report": {"alexa_swan_kettle": {"precision": 1.0, "recall": 1.0, "f1-score": 1.0, "support": 10}, "aqara_hubM2": {"precision": 0.0, "recall": 0.0, "f1-score": 0.0, "support": 4}, "arlo_camera_pro4": {"precision": 0.8333333333333334, "recall": 1.0, "f1-score": 0.9090909090909091, "support": 5}, "boifun_baby": {"precision": 0.5, "recall": 0.2857142857142857, "f1-score": 0.36363636363636365, "support": 7}, "bose_speaker": {"precision": 0.5714285714285714, "recall": 1.0, "f1-score": 0.7272727272727273, "support": 4}, "cosori_air_fryer": {"precision": 0.7692307692307693, "recall": 0.7692307692307693, "f1-score": 0.7692307692307693, "support": 13}, "echodot5": {"precision": 0.5, "recall": 0.4, "f1-score": 0.4444444444444445, "support": 5}, "google_nest_doorbell": {"precision": 0.5, "recall": 0.7272727272727273, "f1-score": 0.5925925925925926, "support": 11}, "google_nest_hub": {"precision": 0.8, "recall": 0.6666666666666666, "f1-score": 0.7272727272727272, "support": 12}, "govee_strip_light": {"precision": 1.0, "recall": 1.0, "f1-score": 1.0, "support": 12}, "iROBOT_roomba": {"precision": 0.0, "recall": 0.0, "f1-score": 0.0, "support": 8}, "nest_cam": {"precision": 1.0, "recall": 0.2222222222222222, "f1-score": 0.3636363636363636, "support": 9}, "netatmo_weather_station": {"precision": 0.3125, "recall": 1.0, "f1-score": 0.47619047619047616, "support": 5}, "petsafe_feeder": {"precision": 0.75, "recall": 0.2727272727272727, "f1-score": 0.39999999999999997, "support": 11}, "ring_chime_pro": {"precision": 0.6363636363636364, "recall": 0.7777777777777778, "f1-score": 0.7000000000000001, "support": 9}, "simplicam": {"precision": 0.9166666666666666, "recall": 1.0, "f1-score": 0.9565217391304348, "support": 11}, "sonos_speaker": {"precision": 0.6363636363636364, "recall": 0.7777777777777778, "f1-score": 0.7000000000000001, "support": 9}, "switchbot_hub_mini_1": {"precision": 0.7, "recall": 1.0, "f1-score": 0.8235294117647058, "support": 14}, "vtech_baby_monitor": {"precision": 1.0, "recall": 1.0, "f1-score": 1.0, "support": 10}, "withings_sleep_analyser": {"precision": 0.9, "recall": 1.0, "f1-score": 0.9473684210526316, "support": 9}, "wiz_smart_bulb": {"precision": 0.42857142857142855, "recall": 0.5, "f1-score": 0.4615384615384615, "support": 6}, "wyze_cam_pan_v2": {"precision": 0.8571428571428571, "recall": 0.75, "f1-score": 0.7999999999999999, "support": 8}, "accuracy": 0.71875, "macro avg": {"precision": 0.6641636772318591, "recall": 0.6886086136086136, "f1-score": 0.6437420639478912, "support": 192}, "weighted avg": {"precision": 0.714746516504329, "recall": 0.71875, "f1-score": 0.6868145342475951, "support": 192}}}
